gargoyle/__init__.py
gargoyle/admin.py
gargoyle/apps.py
gargoyle/builtins.py
gargoyle/checks.py
gargoyle/compat.py
gargoyle/conditions.py
gargoyle/constants.py
gargoyle/decorators.py
gargoyle/helpers.py
gargoyle/manager.py
gargoyle/models.py
gargoyle/nexus_modules.py
gargoyle/proxy.py
gargoyle/signals.py
gargoyle/testutils.py
gargoyle/management/__init__.py
gargoyle/management/commands/__init__.py
gargoyle/management/commands/add_switch.py
gargoyle/management/commands/remove_switch.py
gargoyle/media/css/gargoyle.css
gargoyle/media/img/button-bg.jpg
gargoyle/media/img/delete.png
gargoyle/media/img/edit.png
gargoyle/media/js/gargoyle.js
gargoyle/media/js/jsrender.min.js
gargoyle/media/js/string_score.min.js
gargoyle/migrations/0001_initial.py
gargoyle/migrations/0002_bytes_to_str.py
gargoyle/migrations/__init__.py
gargoyle/templates/gargoyle/index.html
gargoyle/templates/gargoyle/nexus/dashboard.html
gargoyle/templatetags/__init__.py
gargoyle/templatetags/gargoyle_helpers.py
gargoyle/templatetags/gargoyle_tags.py
gargoyle_yplan-2.1.1.dist-info/LICENSE
gargoyle_yplan-2.1.1.dist-info/METADATA
gargoyle_yplan-2.1.1.dist-info/WHEEL
gargoyle_yplan-2.1.1.dist-info/top_level.txt
gargoyle_yplan-2.1.1.dist-info/RECORD
