Metadata-Version: 2.1
Name: gargoyle-yplan
Version: 2.1.1
Summary: Gargoyle is a platform built on top of Django which allows you to switch functionality of your application on and off based on conditions.
Home-page: https://github.com/adamchainz/gargoyle
Author: DISQUS
Author-email: opensource@disqus.com
Maintainer: Adam Johnson
Maintainer-email: me@adamj.eu
License: Apache License 2.0
Platform: UNKNOWN
Classifier: Development Status :: 7 - Inactive
Classifier: Framework :: Django
Classifier: Framework :: Django :: 1.11
Classifier: Framework :: Django :: 2.0
Classifier: Framework :: Django :: 2.1
Classifier: Framework :: Django :: 2.2
Classifier: Intended Audience :: Developers
Classifier: Intended Audience :: System Administrators
Classifier: License :: OSI Approved :: Apache Software License
Classifier: Natural Language :: English
Classifier: Operating System :: OS Independent
Classifier: Programming Language :: Python :: 3 :: Only
Classifier: Programming Language :: Python :: 3
Classifier: Programming Language :: Python :: 3.4
Classifier: Programming Language :: Python :: 3.5
Classifier: Programming Language :: Python :: 3.6
Classifier: Programming Language :: Python
Classifier: Topic :: Software Development
Requires-Python: >=3.4
Requires-Dist: Django (>=1.11)
Requires-Dist: django-modeldict-yplan (>=2.0.0)
Requires-Dist: nexus-yplan (>=2.1.0)
Requires-Dist: django-jsonfield (>=1.2.0)
